easy_encryption_tool/__init__.py
easy_encryption_tool/aes_command.py
easy_encryption_tool/cert_parse.py
easy_encryption_tool/command_perf.py
easy_encryption_tool/common.py
easy_encryption_tool/ecc_command.py
easy_encryption_tool/hmac_command.py
easy_encryption_tool/main.py
easy_encryption_tool/random_str.py
easy_encryption_tool/rsa_command.py
easy_encryption_tool/tool_version.py
easy_encryption_tool-1.2.1.dist-info/METADATA
easy_encryption_tool-1.2.1.dist-info/WHEEL
easy_encryption_tool-1.2.1.dist-info/entry_points.txt
easy_encryption_tool-1.2.1.dist-info/top_level.txt
easy_encryption_tool-1.2.1.dist-info/RECORD
