Metadata-Version: 2.1
Name: easy-encryption-tool
Version: 1.2.1
Home-page: https://cloud.tencent.com/developer/article/2404712
Author: bowenerchen
Author-email: bowener.chen@gmail.com
License: MIT
Keywords: encryption cli tool security aes hmac ecc rsa
Classifier: Programming Language :: Python :: 3
Classifier: License :: OSI Approved :: MIT License
Classifier: Operating System :: OS Independent
Requires-Dist: click
Requires-Dist: cryptography
Requires-Dist: requests
Requires-Dist: pyopenssl
